MANIFEST.in
README.md
requirements-dev.txt
requirements.txt
setup.py
lazy_rpc/__init__.py
lazy_rpc/decolators.py
lazy_rpc/remote.py
lazy_rpc/utils.py
lazy_rpc/version.py
lazy_rpc.egg-info/PKG-INFO
lazy_rpc.egg-info/SOURCES.txt
lazy_rpc.egg-info/dependency_links.txt
lazy_rpc.egg-info/requires.txt
lazy_rpc.egg-info/top_level.txt
lazy_rpc/backend/__init__.py
lazy_rpc/backend/base.py
lazy_rpc/backend/kafka.py