Metadata-Version: 2.1
Name: lazy-rpc
Version: 0.1.2
Summary: rpc module
Home-page: https://github.com/m0cchi/lazy-rpc
Author: m0cchi
Author-email: m0cchi@protonmail.com
License: MIT
Platform: UNKNOWN
Classifier: License :: OSI Approved :: MIT License
Classifier: Programming Language :: Python :: 3
Classifier: Operating System :: OS Independent
Requires-Python: >=3.0
Provides-Extra: dev
